README.md
setup.py
pcrowdstrike_pulumi_gax/__init__.py
pcrowdstrike_pulumi_gax/_inputs.py
pcrowdstrike_pulumi_gax/_utilities.py
pcrowdstrike_pulumi_gax/filevantage_policy.py
pcrowdstrike_pulumi_gax/filevantage_rule_group.py
pcrowdstrike_pulumi_gax/get_sensor_update_policy_builds.py
pcrowdstrike_pulumi_gax/host_group.py
pcrowdstrike_pulumi_gax/outputs.py
pcrowdstrike_pulumi_gax/prevention_policy_linux.py
pcrowdstrike_pulumi_gax/prevention_policy_mac.py
pcrowdstrike_pulumi_gax/prevention_policy_windows.py
pcrowdstrike_pulumi_gax/provider.py
pcrowdstrike_pulumi_gax/pulumi-plugin.json
pcrowdstrike_pulumi_gax/py.typed
pcrowdstrike_pulumi_gax/sensor_update_policy.py
pcrowdstrike_pulumi_gax.egg-info/PKG-INFO
pcrowdstrike_pulumi_gax.egg-info/SOURCES.txt
pcrowdstrike_pulumi_gax.egg-info/dependency_links.txt
pcrowdstrike_pulumi_gax.egg-info/not-zip-safe
pcrowdstrike_pulumi_gax.egg-info/requires.txt
pcrowdstrike_pulumi_gax.egg-info/top_level.txt
pcrowdstrike_pulumi_gax/config/__init__.py
pcrowdstrike_pulumi_gax/config/vars.py