Metadata-Version: 2.1
Name: pcrowdstrike-pulumi-gax
Version: 1.0.12
Summary: A Pulumi package for creating and managing Crowdstrike resources
Home-page: https://github.com/gtheodorio/pulumi-crowdstrike
License: Apache-2.0
Project-URL: Repository, https://github.com/gtheodorio/pulumi-crowdstrike
Keywords: pulumi crowdstrike category/infrastructure
Platform: UNKNOWN
Requires-Python: >=3.8
